anyblok_io/__init__.py
anyblok_io/blok.py
anyblok_io/conftest.py
anyblok_io/release.py
anyblok_io/bloks/__init__.py
anyblok_io/bloks/io/__init__.py
anyblok_io/bloks/io/core.py
anyblok_io/bloks/io/exceptions.py
anyblok_io/bloks/io/exporter.py
anyblok_io/bloks/io/formater.py
anyblok_io/bloks/io/importer.py
anyblok_io/bloks/io/mapping.py
anyblok_io/bloks/io/mixin.py
anyblok_io/bloks/io/tests/__init__.py
anyblok_io/bloks/io/tests/test_core.py
anyblok_io/bloks/io/tests/test_exporter.py
anyblok_io/bloks/io/tests/test_exporter_formater.py
anyblok_io/bloks/io/tests/test_importer.py
anyblok_io/bloks/io/tests/test_importer_formater.py
anyblok_io/bloks/io/tests/test_mapping.py
anyblok_io/bloks/io_csv/__init__.py
anyblok_io/bloks/io_csv/exceptions.py
anyblok_io/bloks/io_csv/exporter.py
anyblok_io/bloks/io_csv/importer.py
anyblok_io/bloks/io_csv/mixin.py
anyblok_io/bloks/io_csv/tests/__init__.py
anyblok_io/bloks/io_csv/tests/test_export.py
anyblok_io/bloks/io_csv/tests/test_import.py
anyblok_io/bloks/io_xml/__init__.py
anyblok_io/bloks/io_xml/exceptions.py
anyblok_io/bloks/io_xml/exporter.py
anyblok_io/bloks/io_xml/importer.py
anyblok_io/bloks/io_xml/tests/__init__.py
anyblok_io/bloks/io_xml/tests/test_export.py
anyblok_io/bloks/io_xml/tests/test_import.py
anyblok_io/test_bloks/__init__.py
anyblok_io/test_bloks/test_blok1/__init__.py
anyblok_io/test_bloks/test_blok1/test.py
anyblok_io/test_bloks/test_blok2/__init__.py
anyblok_io/test_bloks/test_blok2/test.py
anyblok_io/tests/__init__.py
anyblok_io/tests/conftest.py
anyblok_io/tests/test_blok.py
anyblok_io-1.2.0.dist-info/LICENSE
anyblok_io-1.2.0.dist-info/METADATA
anyblok_io-1.2.0.dist-info/WHEEL
anyblok_io-1.2.0.dist-info/entry_points.txt
anyblok_io-1.2.0.dist-info/top_level.txt
anyblok_io-1.2.0.dist-info/RECORD
