Metadata-Version: 2.1
Name: anyblok-io
Version: 1.2.0
Summary: Add importer / exporter to AnyBlok
Home-page: http://docs.anyblok.org/1.2.0
Author: Jean-Sébastien Suzanne
Author-email: js.suzanne@gmail.com
License: MPL2
Platform: UNKNOWN
Classifier: Development Status :: 5 - Production/Stable
Classifier: Intended Audience :: Developers
Classifier: Programming Language :: Python :: 3.6
Classifier: Programming Language :: Python :: 3.7
Classifier: Programming Language :: Python :: 3.8
Classifier: Programming Language :: Python :: 3.9
Classifier: Programming Language :: Python :: 3 :: Only
Classifier: Topic :: Software Development
Classifier: Topic :: Software Development :: Libraries :: Python Modules
Classifier: License :: OSI Approved :: Mozilla Public License 2.0 (MPL 2.0)
Requires-Dist: anyblok (>=1.2.0)
Requires-Dist: lxml
